lltdrek/__init__.py
lltdrek/models/__init__.py
lltdrek/models/exceptions.py
lltdrek/models/flight_condition.py
lltdrek/models/post_processing.py
lltdrek/models/simulation.py
lltdrek/models/types.py
lltdrek/models/wing.py
lltdrek/models/wingpool.py
lltdrek/simulation/__init__.py
lltdrek/simulation/main_equations.py
lltdrek/utils/__init__.py
lltdrek/utils/data.py
lltdrek/utils/geometry.py
lltdrek/utils/lookup.py
lltdrek/utils/timeit.py
lltdrek/utils/velocity.py
lltdrek-1.2.0.dist-info/LICENSE
lltdrek-1.2.0.dist-info/METADATA
lltdrek-1.2.0.dist-info/WHEEL
lltdrek-1.2.0.dist-info/top_level.txt
lltdrek-1.2.0.dist-info/RECORD
