Metadata-Version: 2.2
Name: lltdrek
Version: 1.2.0
Summary: Package description
Author-email: Luis Kuodrek <kuodrek@gmail.com>
Project-URL: Homepage, https://github.com/kuodrek/lltdrek
Classifier: Programming Language :: Python :: 3
Classifier: License :: OSI Approved :: MIT License
Classifier: Operating System :: OS Independent
Requires-Python: >=3.10
License-File: LICENSE
Requires-Dist: matplotlib
Requires-Dist: numpy>=1.26.4
Requires-Dist: scipy>=1.12.0
Provides-Extra: dev
Requires-Dist: pytest; extra == "dev"
Requires-Dist: pytest-cov; extra == "dev"
